CHANGES.txt
README.txt
ZopePublicLicense.txt
bootstrap.py
buildout.cfg
setup.py
src/z3c/__init__.py
src/z3c.optionstorage.egg-info/PKG-INFO
src/z3c.optionstorage.egg-info/SOURCES.txt
src/z3c.optionstorage.egg-info/dependency_links.txt
src/z3c.optionstorage.egg-info/namespace_packages.txt
src/z3c.optionstorage.egg-info/not-zip-safe
src/z3c.optionstorage.egg-info/requires.txt
src/z3c.optionstorage.egg-info/top_level.txt
src/z3c/optionstorage/__init__.py
src/z3c/optionstorage/configure.zcml
src/z3c/optionstorage/interfaces.py
src/z3c/optionstorage/meta.zcml
src/z3c/optionstorage/metaconfigure.py
src/z3c/optionstorage/metadirectives.py
src/z3c/optionstorage/tests.py
src/z3c/optionstorage/vocabulary.py
src/z3c/optionstorage/browser/__init__.py
src/z3c/optionstorage/browser/configure.zcml
src/z3c/optionstorage/browser/meta.zcml
src/z3c/optionstorage/browser/metaconfigure.py
src/z3c/optionstorage/browser/metadirectives.py
src/z3c/optionstorage/browser/optiondict.pt
src/z3c/optionstorage/browser/optionstorage.pt
src/z3c/optionstorage/browser/widgets.py