Metadata-Version: 1.0
Name: z3c.optionstorage
Version: 1.0.7
Summary: Optional Storages -- Persistent, Managable Vocabularies
Home-page: http://pypi.python.org/pypi/z3c.optionstorage
Author: Zope Corporation and Contributors
Author-email: zope-dev@zope.org
License: ZPL 2.1
Keywords: zope3 vocabulary zodb managable
Platform: UNKNOWN
Classifier: Development Status :: 5 - Production/Stable
Classifier: Environment :: Web Environment
Classifier: Intended Audience :: Developers
Classifier: License :: OSI Approved :: Zope Public License
Classifier: Programming Language :: Python
Classifier: Natural Language :: English
Classifier: Operating System :: OS Independent
Classifier: Topic :: Internet :: WWW/HTTP
Classifier: Framework :: Zope3
